jmv/__init__.py
jmv/_frontend.py
jmv/_version.py
jmv/threedp.py
jmv/labextension/build_log.json
jmv/labextension/package.json
jmv/labextension/static/lib_index_js.b25f4ec1da9b47356161.js
jmv/labextension/static/lib_index_js.b25f4ec1da9b47356161.js.map
jmv/labextension/static/lib_index_js.e839095974cb05d30226.js
jmv/labextension/static/lib_index_js.e839095974cb05d30226.js.map
jmv/labextension/static/lib_index_js.f8d276180124c2e36162.js
jmv/labextension/static/lib_index_js.f8d276180124c2e36162.js.map
jmv/labextension/static/lib_index_js.facd3aa84b028b927c5d.js
jmv/labextension/static/lib_index_js.facd3aa84b028b927c5d.js.map
jmv/labextension/static/lib_plugin_js.1168a98aa66260b0ad37.js
jmv/labextension/static/lib_plugin_js.1168a98aa66260b0ad37.js.map
jmv/labextension/static/lib_plugin_js.1f8ab934634565b92d7f.js
jmv/labextension/static/lib_plugin_js.1f8ab934634565b92d7f.js.map
jmv/labextension/static/lib_plugin_js.68f33150d6fac53b9409.js
jmv/labextension/static/lib_plugin_js.68f33150d6fac53b9409.js.map
jmv/labextension/static/lib_plugin_js.77e3cf3d1cd74949c6f6.js
jmv/labextension/static/lib_plugin_js.77e3cf3d1cd74949c6f6.js.map
jmv/labextension/static/remoteEntry.60cb1336b3af332719f8.js
jmv/labextension/static/remoteEntry.60cb1336b3af332719f8.js.map
jmv/labextension/static/remoteEntry.a63dce5a234b8f95e59a.js.map
jmv/labextension/static/remoteEntry.c58d7c392411daaa9219.js.map
jmv/labextension/static/remoteEntry.eac91da1b5294080ad42.js.map
jmv/labextension/static/style.js
jmv/labextension/static/vendors-node_modules_pnpm_css-loader_3_6_0_webpack_5_74_0_node_modules_css-loader_dist_runtim-2ad3b6.619608da0871bcf9c2c5.js
jmv/labextension/static/vendors-node_modules_pnpm_css-loader_3_6_0_webpack_5_74_0_node_modules_css-loader_dist_runtim-2ad3b6.619608da0871bcf9c2c5.js.map
jmv/nbextension/extension.js
jmv/nbextension/index.js
jmv/nbextension/index.js.LICENSE.txt
jmv/nbextension/index.js.map
jmv/tests/__init__.py
jmv/tests/conftest.py
jmv/tests/test_example.py
jmv-0.1.0.dist-info/METADATA
jmv-0.1.0.dist-info/WHEEL
jmv-0.1.0.dist-info/licenses/LICENSE.txt
jmv-0.1.0.dist-info/RECORD
